LICENSE
README.md
stagecoach/LICENSE
stagecoach/README.md
stagecoach/__init__.py
stagecoach/__main__.py
stagecoach/io.py
stagecoach/locking.py
stagecoach/log.py
stagecoach/stagecoach.code-workspace
stagecoach/validation.py
stagecoach/version.py
stagecoach/configuration/__init__.py
stagecoach/configuration/config.yml
stagecoach-0.0.3.dist-info/METADATA
stagecoach-0.0.3.dist-info/WHEEL
stagecoach-0.0.3.dist-info/licenses/LICENSE
stagecoach-0.0.3.dist-info/RECORD
