Metadata-Version: 2.4
Name: stagecoach
Version: 0.0.3
Summary: A pipeline framework for running stages
Author-email: Mart van Rijthoven <mart.vanrijthoven@gmail.com>
License: MIT License
License-File: LICENSE
Classifier: Development Status :: 4 - Beta
Classifier: License :: OSI Approved :: MIT License
Classifier: Operating System :: OS Independent
Classifier: Programming Language :: Python :: 3
Classifier: Programming Language :: Python :: 3.9
Classifier: Programming Language :: Python :: 3.10
Classifier: Programming Language :: Python :: 3.11
Classifier: Programming Language :: Python :: 3.12
Requires-Python: >=3.9
Requires-Dist: click
Requires-Dist: pandas
Requires-Dist: pydantic
Requires-Dist: pyyaml
